Workbook

Sheet Funcionalidades
A1: Lawzora - Inventario de funcionalidades
A2: SaaS de gestion legal multi-jurisdiccion (Espana + Rep. Dominicana). Estado: OK = funcional | GATED = funcional, requiere clave/config (IA, busqueda docs) | STUB = maqueta sin integracion fiscal real.
A3: Area | B3: Funcionalidad | C3: Objetivo (para que sirve) | D3: Como funciona | E3: Estado | F3: Plan minimo
A4: Multi-jurisdiccion y moneda | B4: Dos jurisdicciones (Espana / Rep. Dominicana) | C4: Que un mismo motor sirva a despachos de ES, de RD o que trabajen en ambos paises. | D4: La jurisdiccion es un atributo del despacho y gobierna impuestos e identificadores (no el idioma); adaptadores de cumplimiento por pais. | E4: OK | F4: Esencial
A5: Multi-jurisdiccion y moneda | B5: Terminologia fiscal por pais | C5: Mostrar la terminologia correcta segun el pais (IVA<->ITBIS, IRPF<->ISR, rectificativa<->nota de credito). | D5: Idioma unico espanol con overrides por jurisdiccion; cookie lf_jur segun el despacho. | E5: OK | F5: Esencial
A6: Multi-jurisdiccion y moneda | B6: Validacion de identificadores fiscales | C6: Evitar dar de alta clientes con documentos invalidos. | D6: Valida con digito/letra de control: NIF/NIE/CIF/NIF K-L-M (ES), RNC y Cedula (RD), pasaporte/otro. | E6: OK | F6: Esencial
A7: Multi-jurisdiccion y moneda | B7: Impuestos por pais | C7: Calcular el impuesto correcto en cada factura segun el pais. | D7: ES: IVA 21/10% + retencion IRPF 15/7%. RD: ITBIS 18% (sin retencion). | E7: OK | F7: Esencial
A8: Multi-jurisdiccion y moneda | B8: Multi-moneda EUR / USD / DOP | C8: Facturar y provisionar en la moneda real de cada operacion sin mezclar importes. | D8: Moneda por defecto del despacho, elegible por factura y por provision; paneles e informes desglosan por moneda. | E8: OK | F8: Esencial
A9: Multi-jurisdiccion y moneda | B9: Formato fiscal elegible por factura | C9: Permitir que un despacho emita en formato Espana (Verifactu) o RD (e-CF) factura a factura. | D9: El formato fiscal va desacoplado de la jurisdiccion del despacho; se elige al emitir. | E9: OK | F9: Esencial
A10: Autenticacion y seguridad | B10: Alta de despacho (onboarding) | C10: Que un despacho nuevo se registre y empiece a usar la plataforma solo. | D10: Crea el tenant, siembra el RBAC y el primer FIRM_ADMIN con auto-login. | E10: OK | F10: Esencial
A11: Autenticacion y seguridad | B11: Login email + contrasena (multi-despacho) | C11: Entrar a la cuenta, incluso si existe en varios despachos. | D11: Email+password; si la cuenta esta en varios despachos, se elige cual al iniciar sesion. | E11: OK | F11: Esencial
A12: Autenticacion y seguridad | B12: Verificacion en dos pasos (2FA) y login social | C12: Reforzar la seguridad de la cuenta y simplificar el acceso. | D12: MFA opcional + inicio de sesion con Google o Microsoft. | E12: OK | F12: Esencial
A13: Autenticacion y seguridad | B13: Sesiones JWT con rotacion segura | C13: Mantener la sesion sin exponer tokens y cortar sesiones robadas. | D13: Access en memoria + refresh en cookie httpOnly; rotacion con deteccion de reuso (un token reutilizado revoca todas las sesiones). | E13: OK | F13: Esencial
A14: Autenticacion y seguridad | B14: Recuperacion y cambio de contrasena | C14: Recuperar acceso y forzar cambio en cuentas creadas por staff. | D14: Enlace por correo self-service + cambio forzado en el primer acceso. | E14: OK | F14: Esencial
... A121: Plataforma SaaS (tu negocio) | B121: Muro de suscripcion | C121: Bloquear el acceso si no pagan. | D121: Interceptor: sin acceso (prueba caducada sin pago) devuelve 402 + muro de suscripcion. | E121: OK | F121: Plataforma

Sheet Resumen
A1: Resumen por area
A2: Area | B2: Funcionalidades | C2: Detalle
A3: Multi-jurisdiccion y moneda | B3: =COUNTIF(Funcionalidades!$A$4:$A$121,A3) | C3: ="OK: "&COUNTIFS(Funcionalidades!$A$4:$A$121,A3,Funcionalidades!$E$4:$E$121,"OK")&" | GATED: "&COUNTIFS(Funcionalidades!$A$4:$A$121,A3,Funcionalidades!$E$4:$E$121,"GATED")&" | STUB: "&COUNTIFS(Funcionalidades!$A$4:$A$121,A3,Funcionalidades!$E$4:$E$121,"STUB")
A4: Autenticacion y seguridad | B4: =COUNTIF(Funcionalidades!$A$4:$A$121,A4) | C4: ="OK: "&COUNTIFS(Funcionalidades!$A$4:$A$121,A4,Funcionalidades!$E$4:$E$121,"OK")&" | GATED: "&COUNTIFS(Funcionalidades!$A$4:$A$121,A4,Funcionalidades!$E$4:$E$121,"GATED")&" | STUB: "&COUNTIFS(Funcionalidades!$A$4:$A$121,A4,Funcionalidades!$E$4:$E$121,"STUB")
A5: Clientes (CRM) | B5: =COUNTIF(Funcionalidades!$A$4:$A$121,A5) | C5: ="OK: "&COUNTIFS(Funcionalidades!$A$4:$A$121,A5,Funcionalidades!$E$4:$E$121,"OK")&" | GATED: "&COUNTIFS(Funcionalidades!$A$4:$A$121,A5,Funcionalidades!$E$4:$E$121,"GATED")&" | STUB: "&COUNTIFS(Funcionalidades!$A$4:$A$121,A5,Funcionalidades!$E$4:$E$121,"STUB")
A6: KYC / Prevencion de blanqueo | B6: =COUNTIF(Funcionalidades!$A$4:$A$121,A6) | C6: ="OK: "&COUNTIFS(Funcionalidades!$A$4:$A$121,A6,Funcionalidades!$E$4:$E$121,"OK")&" | GATED: "&COUNTIFS(Funcionalidades!$A$4:$A$121,A6,Funcionalidades!$E$4:$E$121,"GATED")&" | STUB: "&COUNTIFS(Funcionalidades!$A$4:$A$121,A6,Funcionalidades!$E$4:$E$121,"STUB")
A7: Captacion (Leads) | B7: =COUNTIF(Funcionalidades!$A$4:$A$121,A7) | C7: ="OK: "&COUNTIFS(Funcionalidades!$A$4:$A$121,A7,Funcionalidades!$E$4:$E$121,"OK")&" | GATED: "&COUNTIFS(Funcionalidades!$A$4:$A$121,A7,Funcionalidades!$E$4:$E$121,"GATED")&" | STUB: "&COUNTIFS(Funcionalidades!$A$4:$A$121,A7,Funcionalidades!$E$4:$E$121,"STUB")
A8: Expedientes | B8: =COUNTIF(Funcionalidades!$A$4:$A$121,A8) | C8: ="OK: "&COUNTIFS(Funcionalidades!$A$4:$A$121,A8,Funcionalidades!$E$4:$E$121,"OK")&" | GATED: "&COUNTIFS(Funcionalidades!$A$4:$A$121,A8,Funcionalidades!$E$4:$E$121,"GATED")&" | STUB: "&COUNTIFS(Funcionalidades!$A$4:$A$121,A8,Funcionalidades!$E$4:$E$121,"STUB")
A9: Tareas y plazos procesales | B9: =COUNTIF(Funcionalidades!$A$4:$A$121,A9) | C9: ="OK: "&COUNTIFS(Funcionalidades!$A$4:$A$121,A9,Funcionalidades!$E$4:$E$121,"OK")&" | GATED: "&COUNTIFS(Funcionalidades!$A$4:$A$121,A9,Funcionalidades!$E$4:$E$121,"GATED")&" | STUB: "&COUNTIFS(Funcionalidades!$A$4:$A$121,A9,Funcionalidades!$E$4:$E$121,"STUB")
A10: Tiempo (time tracking) | B10: =COUNTIF(Funcionalidades!$A$4:$A$121,A10) | C10: ="OK: "&COUNTIFS(Funcionalidades!$A$4:$A$121,A10,Funcionalidades!$E$4:$E$121,"OK")&" | GATED: "&COUNTIFS(Funcionalidades!$A$4:$A$121,A10,Funcionalidades!$E$4:$E$121,"GATED")&" | STUB: "&COUNTIFS(Funcionalidades!$A$4:$A$121,A10,Funcionalidades!$E$4:$E$121,"STUB")
A11: Documentos y firma | B11: =COUNTIF(Funcionalidades!$A$4:$A$121,A11) | C11: ="OK: "&COUNTIFS(Funcionalidades!$A$4:$A$121,A11,Funcionalidades!$E$4:$E$121,"OK")&" | GATED: "&COUNTIFS(Funcionalidades!$A$4:$A$121,A11,Funcionalidades!$E$4:$E$121,"GATED")&" | STUB: "&COUNTIFS(Funcionalidades!$A$4:$A$121,A11,Funcionalidades!$E$4:$E$121,"STUB")
A12: Facturacion y fiscal | B12: =COUNTIF(Funcionalidades!$A$4:$A$121,A12) | C12: ="OK: "&COUNTIFS(Funcionalidades!$A$4:$A$121,A12,Funcionalidades!$E$4:$E$121,"OK")&" | GATED: "&COUNTIFS(Funcionalidades!$A$4:$A$121,A12,Funcionalidades!$E$4:$E$121,"GATED")&" | STUB: "&COUNTIFS(Funcionalidades!$A$4:$A$121,A12,Funcionalidades!$E$4:$E$121,"STUB")
A13: Provision de fondos | B13: =COUNTIF(Funcionalidades!$A$4:$A$121,A13) | C13: ="OK: "&COUNTIFS(Funcionalidades!$A$4:$A$121,A13,Funcionalidades!$E$4:$E$121,"OK")&" | GATED: "&COUNTIFS(Funcionalidades!$A$4:$A$121,A13,Funcionalidades!$E$4:$E$121,"GATED")&" | STUB: "&COUNTIFS(Funcionalidades!$A$4:$A$121,A13,Funcionalidades!$E$4:$E$121,"STUB")
A14: Facturacion programada | B14: =COUNTIF(Funcionalidades!$A$4:$A$121,A14) | C14: ="OK: "&COUNTIFS(Funcionalidades!$A$4:$A$121,A14,Funcionalidades!$E$4:$E$121,"OK")&" | GATED: "&COUNTIFS(Funcionalidades!$A$4:$A$121,A14,Funcionalidades!$E$4:$E$121,"GATED")&" | STUB: "&COUNTIFS(Funcionalidades!$A$4:$A$121,A14,Funcionalidades!$E$4:$E$121,"STUB")
... A28: Plataforma SaaS (tu negocio) | B28: =COUNTIF(Funcionalidades!$A$4:$A$121,A28) | C28: ="OK: "&COUNTIFS(Funcionalidades!$A$4:$A$121,A28,Funcionalidades!$E$4:$E$121,"OK")&" | GATED: "&COUNTIFS(Funcionalidades!$A$4:$A$121,A28,Funcionalidades!$E$4:$E$121,"GATED")&" | STUB: "&COUNTIFS(Funcionalidades!$A$4:$A$121,A28,Funcionalidades!$E$4:$E$121,"STUB")
A29: TOTAL | B29: =SUM(B3:B28) | C29: ="OK: "&COUNTIF(Funcionalidades!$E$4:$E$121,"OK")&" | GATED: "&COUNTIF(Funcionalidades!$E$4:$E$121,"GATED")&" | STUB: "&COUNTIF(Funcionalidades!$E$4:$E$121,"STUB")
